fttjax/__init__.py
fttjax/ft_transformer.py
fttjax-0.1.1.dist-info/LICENSE
fttjax-0.1.1.dist-info/METADATA
fttjax-0.1.1.dist-info/WHEEL
fttjax-0.1.1.dist-info/top_level.txt
fttjax-0.1.1.dist-info/RECORD
