Metadata-Version: 2.1
Name: fttjax
Version: 0.1.1
Summary: Feature Tokenizer + Transformer - JAX
Home-page: https://github.com/github/fttransformer
Author: Tarun Agrawal
Author-email: tarun@axra.org
License: MIT
Keywords: artificial intelligence,transformers,attention mechanism,tabular data
Classifier: Development Status :: 4 - Beta
Classifier: Intended Audience :: Developers
Classifier: Topic :: Scientific/Engineering :: Artificial Intelligence
Classifier: License :: OSI Approved :: MIT License
Classifier: Programming Language :: Python :: 3.11
License-File: LICENSE
Requires-Dist: einops >=0.5
Requires-Dist: jax >=0.4
Requires-Dist: flax >=0.7
